group_genie/__init__.py
group_genie/datastore.py
group_genie/logging.py
group_genie/message.py
group_genie/preferences.py
group_genie/secrets.py
group_genie/session.py
group_genie/utils.py
group_genie/agent/__init__.py
group_genie/agent/approval.py
group_genie/agent/base.py
group_genie/agent/factory.py
group_genie/agent/runner.py
group_genie/agent/provider/__init__.py
group_genie/agent/provider/openai/__init__.py
group_genie/agent/provider/openai/agent.py
group_genie/agent/provider/openai/utils.py
group_genie/agent/provider/pydantic_ai/__init__.py
group_genie/agent/provider/pydantic_ai/base.py
group_genie/agent/provider/pydantic_ai/group.py
group_genie/agent/provider/pydantic_ai/utils.py
group_genie/agent/provider/pydantic_ai/agent/__init__.py
group_genie/agent/provider/pydantic_ai/agent/default.py
group_genie/agent/provider/pydantic_ai/agent/prompt.py
group_genie/reasoner/__init__.py
group_genie/reasoner/base.py
group_genie/reasoner/factory.py
group_genie/reasoner/runner.py
group_genie-0.0.2.dist-info/METADATA
group_genie-0.0.2.dist-info/WHEEL
group_genie-0.0.2.dist-info/licenses/LICENSE
group_genie-0.0.2.dist-info/RECORD
