Metadata-Version: 2.4
Name: group-genie
Version: 0.0.2
Summary: Group Genie
Author-email: Martin Krasser <martin@gradion.ai>
License-Expression: Apache-2.0
License-File: LICENSE
Requires-Python: <3.15,>=3.11
Requires-Dist: aiofiles>=24.1.0
Requires-Dist: group-sense<0.1,>=0.0.4
Provides-Extra: openai
Requires-Dist: openai-agents<0.6,>=0.5.0; extra == 'openai'
